{
  "chapterInfo": {
    "class": 6,
    "subject": "History",
    "chapterNumber": 5,
    "chapterName": "India, That Is Bharat",
    "totalQuestions": 30,
    "difficulty": "medium"
  },
  "questions": [
    {
      "id": 1,
      "question": "According to the Rig Veda, what was the name given to the northwest region of the Indian Subcontinent?",
      "options": [
        "Jambudvīpa",
        "Bhāratavarsha",
        "Sapta Sindhava",
        "Aryavarta"
      ],
      "correct": 2,
      "explanation": "The Rig Veda, India's most ancient text, names the northwest region 'Sapta Sindhava', which means 'the land of the seven rivers'.",
      "topic": "Ancient Indian Names",
      "difficulty": "easy"
    },
    {
      "id": 2,
      "question": "What is the literal meaning of the term 'Jambudvīpa'?",
      "options": [
        "Land of the snowy mountains",
        "The island of the fruit of the jamun tree",
        "Country of the Bharatas",
        "Land of the seven rivers"
      ],
      "correct": 1,
      "explanation": "'Jambudvīpa' means 'the island of the fruit of the jamun tree', a common tree native to India.",
      "topic": "Ancient Indian Names",
      "difficulty": "easy"
    },
    {
      "id": 3,
      "question": "Which emperor, around 250 BCE, used the name 'Jambudvīpa' in an inscription to describe his empire?",
      "options": [
        "Chandragupta Maurya",
        "Harshavardhana",
        "Samudragupta",
        "Ashoka"
      ],
      "correct": 3,
      "explanation": "Emperor Ashoka used the name 'Jambudvīpa' in one of his inscriptions to describe the whole of India.",
      "topic": "Ancient Indian Names",
      "difficulty": "easy"
    },
    {
      "id": 4,
      "question": "The name 'Bhāratavarsha' means which of the following?",
      "options": [
        "The land of the Indus",
        "The island of Jambu",
        "The country of the Bharatas",
        "The southern continent"
      ],
      "correct": 2,
      "explanation": "The term 'Bhāratavarsha' means 'the country of the Bharatas'. The Bharatas were one of the main Vedic groups of people mentioned in the Rig Veda.",
      "topic": "Ancient Indian Names",
      "difficulty": "easy"
    },
    {
      "id": 5,
      "question": "Which ancient Indian text is quoted as defining Bhārata as 'The country that lies north of the ocean and south of the snowy mountains'?",
      "options": [
        "The Rig Veda",
        "The Mahābhārata",
        "The Vishnu Purāņa",
        "The Constitution of India"
      ],
      "correct": 2,
      "explanation": "The Vishnu Purāņa contains the verse 'uttaram yat samudrasya himādreścaiva dakşiņam varşam tad bhāratam nāma', which defines Bhārata geographically.",
      "topic": "Ancient Indian Names",
      "difficulty": "easy"
    },
    {
      "id": 6,
      "question": "The names 'Hind', 'Hidu', or 'Hindu' used by the ancient Persians were derived from which ancient name?",
      "options": [
        "Himalaya",
        "Bharata",
        "Sindhu",
        "Ganga"
      ],
      "correct": 2,
      "explanation": "The earliest Persian records referred to the region of the Indus River as 'Hind', 'Hidu', or 'Hindu', which are adaptations of the original name 'Sindhu'.",
      "topic": "Foreign Names for India",
      "difficulty": "easy"
    },
    {
      "id": 7,
      "question": "Who was Xuanzang?",
      "options": [
        "A Persian emperor who conquered the Indus region",
        "A Greek geographer who named India 'Indoi'",
        "A Chinese traveler who visited India in the 7th century CE",
        "An ancient Indian king mentioned in the Rig Veda"
      ],
      "correct": 2,
      "explanation": "Xuanzang was a famous Chinese scholar who travelled to India in the 7th century CE, collected Buddhist texts, and stayed for 17 years.",
      "topic": "Foreign Names for India",
      "difficulty": "easy"
    },
    {
      "id": 8,
      "question": "What is the opening phrase of the Indian Constitution that defines the country's name?",
      "options": [
        "'Bharat, that is Hindustan'",
        "'The Republic of India'",
        "'India, that is Bharat'",
        "'Jambudvīpa, also known as India'"
      ],
      "correct": 2,
      "explanation": "The very first article of the Indian Constitution begins with the phrase 'India, that is Bharat', officially recognizing both names.",
      "topic": "Modern Naming",
      "difficulty": "easy"
    },
    {
      "id": 9,
      "question": "The Mahābhārata, an ancient epic, lists many regions of India. Which of the following is NOT mentioned in the provided text as being in the Mahābhārata?",
      "options": [
        "Kāshmīra (Kashmir)",
        "Vanga (Bengal)",
        "Goa",
        "Kaccha (Kutch)"
      ],
      "correct": 2,
      "explanation": "The text mentions that the Mahābhārata lists regions like Kāshmīra, Vanga, Prāgjyotisha, Kaccha, and Kerala, but it does not mention Goa.",
      "topic": "Ancient Indian Names",
      "difficulty": "easy"
    },
    {
      "id": 10,
      "question": "In which ancient text does the name 'Bharata' first appear, referring to a group of people?",
      "options": [
        "Vishnu Purāņa",
        "Mahābhārata",
        "Ashoka's Inscriptions",
        "Rig Veda"
      ],
      "correct": 3,
      "explanation": "The name 'Bharata' first appears in the Rig Veda, where it refers to one of the main Vedic groups of people.",
      "topic": "Ancient Indian Names",
      "difficulty": "easy"
    },
    {
      "id": 11,
      "question": "Why did the ancient Greeks refer to the Indian subcontinent as 'Indoi' or 'Indike'?",
      "options": [
        "They misheard the name from Chinese traders.",
        "They dropped the initial 'h' from the Persian word 'Hindu' because the sound didn't exist in Greek.",
        "It was the name given by Emperor Ashoka.",
        "It was a direct translation of 'Jambudvīpa'."
      ],
      "correct": 1,
      "explanation": "The Greeks learned the name from the Persians ('Hindu'). They adapted it to 'Indoi' because their language lacked the initial 'h' sound.",
      "topic": "Foreign Names for India",
      "difficulty": "medium"
    },
    {
      "id": 12,
      "question": "The name 'Sapta Sindhava' meaning 'land of the seven rivers' was most appropriate for which geographical region shown on the map?",
      "options": [
        "The southern peninsula near Kerala",
        "The eastern region near Bengal",
        "The central Deccan plateau",
        "The northwestern region including the Indus and its tributaries"
      ],
      "correct": 3,
      "explanation": "The name 'Sapta Sindhava' points to the northwest of the subcontinent, which is dominated by the Indus river system, including tributaries like the Jhelum, Chenab, Ravi, Sutlej, and Beas.",
      "topic": "Geography and Naming",
      "difficulty": "medium"
    },
    {
      "id": 13,
      "question": "In ancient Persian, the word 'Hindu' was a purely geographical term. What did it signify?",
      "options": [
        "A follower of the Hindu religion",
        "A person from the region of the Sindhu (Indus) river",
        "Someone who spoke the Sanskrit language",
        "An inhabitant of the snowy mountains"
      ],
      "correct": 1,
      "explanation": "The text explicitly notes that in ancient Persian, 'Hindu' was a geographical term referring to the land and people around the Sindhu river, not the religion.",
      "topic": "Foreign Names for India",
      "difficulty": "medium"
    },
    {
      "id": 14,
      "question": "Which modern Indian state corresponds roughly to the region of 'Prāgjyotisha' mentioned in the Mahābhārata?",
      "options": [
        "Kerala",
        "Haryana",
        "Assam",
        "Gujarat"
      ],
      "correct": 2,
      "explanation": "The text states that Prāgjyotisha from the Mahābhārata corresponds roughly to today's Assam.",
      "topic": "Ancient and Modern Geography",
      "difficulty": "medium"
    },
    {
      "id": 15,
      "question": "How did the Chinese name for India, 'Yintu', evolve?",
      "options": [
        "It was a translation of 'Bhārata'.",
        "It came directly from the Greek name 'Indoi'.",
        "It was derived from 'Sindhu' through Persian and other intermediate steps (Sindhu -> Hindhu -> Indu -> Yindu).",
        "It was named after a Chinese explorer."
      ],
      "correct": 2,
      "explanation": "The text shows a clear linguistic path for 'Yintu': Sindhu → Hindhu → Indu → Yindu, showing its origin from the name of the river.",
      "topic": "Foreign Names for India",
      "difficulty": "medium"
    },
    {
      "id": 16,
      "question": "According to the text, Ashoka's description of 'Jambudvīpa' covered a larger area than modern-day India. What other present-day countries were included?",
      "options": [
        "China, Nepal, and Sri Lanka",
        "Iran, Iraq, and Turkey",
        "Bangladesh, Pakistan, and parts of Afghanistan",
        "Thailand, Myanmar, and Malaysia"
      ],
      "correct": 2,
      "explanation": "The text states that in Ashoka's time, 'Jambudvīpa' included what is today Bangladesh, Pakistan, as well as parts of Afghanistan.",
      "topic": "Historical Geography",
      "difficulty": "medium"
    },
    {
      "id": 17,
      "question": "The name 'Bhāratavarsha' is linked to the Bharatas, a group of people from the Rig Veda. What does this origin suggest?",
      "options": [
        "The name was given by foreign invaders.",
        "The name originated from the people living within the land.",
        "The name is based purely on a geographical feature.",
        "The name was invented in modern times."
      ],
      "correct": 1,
      "explanation": "Since the Bharatas were an indigenous Vedic group, the name 'Bhāratavarsha' is an example of a name that originated from the inhabitants themselves.",
      "topic": "Ancient Indian Names",
      "difficulty": "medium"
    },
    {
      "id": 18,
      "question": "An ancient Tamil poem praises a king whose fame stretched from 'Kumari in the south' to 'the great mountain in the north'. What does this imply?",
      "options": [
        "Ancient Tamils only knew about South India.",
        "They had a clear concept of the Indian subcontinent as a single geographical unit.",
        "They believed the world was flat.",
        "The king had conquered the entire world."
      ],
      "correct": 1,
      "explanation": "This description, mentioning the southernmost tip (Cape Kumari) and the northernmost mountains (Himalayas), shows a well-developed geographical awareness of the entire subcontinent.",
      "topic": "Historical Geography",
      "difficulty": "medium"
    },
    {
      "id": 19,
      "question": "The term 'Hindustan' became common later. According to the text, when was it first used and in what language?",
      "options": [
        "In a Greek text 2,000 years ago",
        "In a Chinese text in the 7th century CE",
        "In a Persian inscription 1,800 years ago",
        "In the Indian Constitution in 1950"
      ],
      "correct": 2,
      "explanation": "The text specifies that 'Hindustan' was first used in a Persian inscription about 1,800 years ago.",
      "topic": "Foreign Names for India",
      "difficulty": "medium"
    },
    {
      "id": 20,
      "question": "The definition of Bhārata in the Vishnu Purāņa refers to the 'snowy mountains'. Which mountain range does this refer to?",
      "options": [
        "The Alps",
        "The Andes",
        "The Himalayas",
        "The Urals"
      ],
      "correct": 2,
      "explanation": "The 'snowy mountains' forming the northern border of the Indian subcontinent are the Himalayas.",
      "topic": "Geography and Naming",
      "difficulty": "medium"
    },
    {
      "id": 21,
      "question": "What is the most significant difference between the origin of the name 'Bhārata' and the name 'India'?",
      "options": [
        "'Bhārata' is a modern name, while 'India' is ancient.",
        "'Bhārata' originated from a group of people within the subcontinent, while 'India' originated from foreigners adapting a river's name.",
        "'India' refers to a smaller area than 'Bhārata'.",
        "'India' is a religious term, while 'Bhārata' is geographical."
      ],
      "correct": 1,
      "explanation": "'Bhārata' comes from the indigenous Bharata people, an 'insider' name. 'India' comes from 'Sindhu' as adapted by Persians and then Greeks, an 'outsider' name.",
      "topic": "Comparative Analysis",
      "difficulty": "hard"
    },
    {
      "id": 22,
      "question": "The Chinese word for India, 'Tianzhu', had a dual meaning: a derivative of 'Sindhu' and 'heavenly master'. What does this dual meaning suggest about the ancient Chinese perception of India?",
      "options": [
        "They were confused about India's actual name.",
        "They saw India as both a geographical place and a land of great spiritual importance, the land of the Buddha.",
        "They believed India was ruled by a king from heaven.",
        "They thought 'Sindhu' and 'heaven' were the same word in Sanskrit."
      ],
      "correct": 1,
      "explanation": "The geographical origin ('Sindhu') is clear, but the alternate meaning 'heavenly master' reflects the deep respect the Chinese had for India as the origin of Buddhism.",
      "topic": "Cultural Interpretation",
      "difficulty": "hard"
    },
    {
      "id": 23,
      "question": "Why, according to the text, is it hard for historians to determine when a name for the entire subcontinent first appeared in Indian literature?",
      "options": [
        "Ancient Indians did not have a name for the whole subcontinent.",
        "All ancient texts were destroyed.",
        "Ancient Indian texts are difficult to date with precision.",
        "Ancient Indians were not good with geography."
      ],
      "correct": 2,
      "explanation": "The text explicitly states, 'Because ancient Indian texts are difficult to date, this is not an easy question to answer,' highlighting the challenge of chronology.",
      "topic": "Historiography",
      "difficulty": "hard"
    },
    {
      "id": 24,
      "question": "Comparing the scope of 'Sapta Sindhava' (Rig Veda) and 'Bhāratavarsha' (Mahābhārata), what can we infer about the evolution of geographical knowledge among ancient Indians?",
      "options": [
        "Knowledge became less accurate over time.",
        "The focus shifted from rivers to mountains.",
        "It expanded from a specific northwestern region to an understanding of the entire subcontinent.",
        "It remained unchanged for centuries."
      ],
      "correct": 2,
      "explanation": "'Sapta Sindhava' refers to a specific river-based region. 'Bhāratavarsha' in the Mahābhārata refers to the entire subcontinent, showing a significant expansion of the geographical horizon.",
      "topic": "Historical Analysis",
      "difficulty": "hard"
    },
    {
      "id": 25,
      "question": "The Indian Constitution officially uses 'India, that is Bharat'. What is the most likely significance of adopting both names?",
      "options": [
        "To confuse other countries.",
        "A compromise between two political factions.",
        "To honor both the internationally recognized name derived from foreigners and the ancient, indigenous name.",
        "To have a long official name like other countries."
      ],
      "correct": 2,
      "explanation": "Using both names validates the country's identity on the world stage ('India') while also honoring its deep-rooted historical and cultural name ('Bharat').",
      "topic": "Modern Naming",
      "difficulty": "hard"
    },
    {
      "id": 26,
      "question": "The evolution of 'Sindhu' to 'Hind' (Persian) and then 'Indoi' (Greek) is a prime example of what process?",
      "options": [
        "Literal translation",
        "Deliberate alteration",
        "Linguistic adaptation based on the phonetics of different languages",
        "Random chance"
      ],
      "correct": 2,
      "explanation": "Each language adapted the foreign word 'Sindhu' to fit its own sounds and rules. For example, Persians changed 'S' to 'H', and Greeks dropped the 'H' they couldn't pronounce.",
      "topic": "Linguistics",
      "difficulty": "hard"
    },
    {
      "id": 27,
      "question": "The text mentions the Mahābhārata lists many regions like Kāshmīra, Vanga, and Kerala. What does the existence of this list within the epic imply about the subcontinent at that time?",
      "options": [
        "The entire subcontinent was a single, unified empire with no internal divisions.",
        "The author had never traveled and was guessing the names.",
        "The subcontinent was recognized as being composed of numerous distinct regions or kingdoms.",
        "People only identified with their local village."
      ],
      "correct": 2,
      "explanation": "The act of listing numerous distinct regions suggests a political and cultural landscape where these individual identities (like Kashmir, Bengal, etc.) were well-known and significant, likely as different kingdoms or cultural zones.",
      "topic": "Political and Cultural Inference",
      "difficulty": "hard"
    },
    {
      "id": 28,
      "question": "Why is the distinction that 'Hindu' was originally a geographical term, not a religious one, crucial for a student of history?",
      "options": [
        "It is not an important distinction.",
        "It proves that the Hindu religion is not actually from India.",
        "It helps to avoid anachronism, which is the error of applying modern concepts and meanings to the past.",
        "It shows that Persians were not religious."
      ],
      "correct": 2,
      "explanation": "Understanding that words change meaning over time is a fundamental historical skill. Applying the modern religious meaning of 'Hindu' to ancient Persia would misinterpret their records.",
      "topic": "Historical Thinking",
      "difficulty": "hard"
    },
    {
      "id": 29,
      "question": "This chapter draws on the Rig Veda, Mahābhārata, Persian inscriptions, and Chinese travelogues. Why is using such a wide variety of sources important for historical study?",
      "options": [
        "It is not important; one good source is enough.",
        "To make the chapter longer and more difficult to read.",
        "Different sources provide different perspectives (e.g., insider vs. outsider) and can be used to corroborate information, creating a more reliable account.",
        "Only religious texts are trustworthy for ancient history."
      ],
      "correct": 2,
      "explanation": "Historians build a stronger case by synthesizing information from multiple, diverse sources. An insider's epic (Mahābhārata) and an outsider's account (Xuanzang) provide different but equally valuable viewpoints that enrich our understanding.",
      "topic": "Historiography",
      "difficulty": "hard"
    },
    {
      "id": 30,
      "question": "Why might a foreign power, such as the Persian empire, be among the first to create a name for a part of India they interacted with?",
      "options": [
        "They wanted to give a gift to the local people.",
        "The local people had no name for their own land.",
        "For administrative purposes related to conquest and trade, it is necessary to identify and name territories.",
        "They wanted to practice their language skills."
      ],
      "correct": 2,
      "explanation": "When an empire conquers or controls a region, it needs to name it for military records, tax collection, and general administration. This practical need often drives the naming of foreign lands.",
      "topic": "Historical Motivation",
      "difficulty": "hard"
    }
  ]
}